Metadata-Version: 2.1
Name: distributions-caluclator
Version: 1.0
Summary: Gaussian & Binomial distributions
Author: Farouk EL
Author-email: farouk.sallak@outlook.com
